{
  "key": "streaming-movie:bilibili-BV1uX4y1q7Do",
  "data": {
    "id": "bilibili-BV1uX4y1q7Do",
    "title": "看完练完即精通！Studio one 6录音混音全功能详解，开始跟练吧",
    "description": "此教程作为正式录音混音教程的补充教程，要知道录音混音的一切开始于精通宿主。所以我们全面的讲解了Studio one这款软件的所有关于录音混音的功能。大家可以跟练学习，无需多久，即可完全掌握此软件。各位加油！",
    "year": 2023,
    "duration": "8h 20m",
    "durationSeconds": 30053,
    "genres": [
      "视频教程",
      "录音",
      "有声书",
      "经验分享",
      "插件"
    ],
    "rating": 0,
    "quality": "720p",
    "poster": "//i1.hdslb.com/bfs/archive/b89a303421f568a8cd8f34e649f295aa9f831bad.jpg",
    "backdrop": "//i1.hdslb.com/bfs/archive/b89a303421f568a8cd8f34e649f295aa9f831bad.jpg",
    "source": "bilibili",
    "sourceUrl": "https://www.bilibili.com/video/BV1uX4y1q7Do",
    "sourceLicense": "Free to Watch",
    "videoUrl": "https://www.bilibili.com/video/BV1uX4y1q7Do",
    "videoType": "bilibili",
    "embedUrl": "https://player.bilibili.com/player.html?bvid=BV1uX4y1q7Do&autoplay=0&high_quality=1",
    "isEmbeddable": true,
    "languages": [
      {
        "code": "ja",
        "label": "Japanese (Original)",
        "isOriginal": true,
        "isDubbed": false,
        "audioFormat": "Stereo"
      },
      {
        "code": "zh",
        "label": "Chinese (Subtitled)",
        "isOriginal": false,
        "isDubbed": false,
        "audioFormat": "Stereo"
      }
    ],
    "subtitles": [
      {
        "code": "zh",
        "label": "Chinese",
        "isDefault": true
      },
      {
        "code": "en",
        "label": "English",
        "isDefault": false
      }
    ],
    "is4K": false,
    "isFree": true,
    "addedAt": "2023-06-24T09:18:24.000Z"
  },
  "createdAt": 1778217027286,
  "expiresAt": 1778303427286
}