{
  "key": "streaming-movie:openflix-Bonanza_pd",
  "data": {
    "id": "openflix-Bonanza_pd",
    "title": "Bonanza public domain episodes",
    "description": "Public domain episodes of the TV show Bonanza",
    "year": 0,
    "duration": "Unknown",
    "durationSeconds": 0,
    "genres": [],
    "rating": 2,
    "quality": "Unknown",
    "poster": "https://archive.org/services/img/Bonanza_pd",
    "backdrop": "https://archive.org/services/img/Bonanza_pd",
    "source": "openflix",
    "sourceUrl": "https://archive.org/details/Bonanza_pd",
    "sourceLicense": "Public Domain / Open Source",
    "videoUrl": "https://archive.org/download/Bonanza_pd/Bonanza%20s01e19.mp4",
    "videoType": "direct",
    "isEmbeddable": true,
    "languages": [
      {
        "code": "en",
        "label": "English (Original)",
        "isOriginal": true,
        "isDubbed": false,
        "audioFormat": "Stereo"
      }
    ],
    "subtitles": [
      {
        "code": "en",
        "label": "English",
        "isDefault": true
      }
    ],
    "is4K": false,
    "isFree": true,
    "addedAt": "2026-05-09T03:42:32.263Z"
  },
  "createdAt": 1778337992646,
  "expiresAt": 1778424392646
}